{
  "anonymous": false,
  "attributes": [
    {
      "name": "Survey Configuration",
      "values": [
        ""
      ]
    }
  ],
  "bridgedResources": [

  ],
  "categorizations": [

  ],
  "customHeadContent": "",
  "description": "",
  "name": "Survey Template Scale",
  "notes": "Add questions to the Questions from source as d-FieldNameFromSource if you are taking in any particular information from the source, such as ticket number.",
  "pages": [
    {
      "advanceCondition": null,
      "displayCondition": null,
      "displayPage": null,
      "elements": [
        {
          "type": "section",
          "renderType": null,
          "name": "Ticket Information Section",
          "title": null,
          "visible": true,
          "omitWhenHidden": null,
          "renderAttributes": {
          },
          "elements": [
            {
              "type": "content",
              "renderType": "html",
              "name": "Ticket Information HTML",
              "text": "<div>\n  <p><strong>Example Source Data: </strong>${values('d-Example Source Data')}</p>\n</div>",
              "visible": true,
              "renderAttributes": {
              }
            }
          ]
        },
        {
          "type": "section",
          "renderType": null,
          "name": "Survey Scale Layout",
          "title": null,
          "visible": true,
          "omitWhenHidden": null,
          "renderAttributes": {
          },
          "elements": [
            {
              "type": "field",
              "name": "Example Question 1",
              "label": "Example Question 1",
              "key": "f910",
              "defaultValue": "",
              "defaultResourceName": null,
              "visible": true,
              "enabled": true,
              "required": false,
              "requiredMessage": null,
              "omitWhenHidden": null,
              "pattern": null,
              "constraints": [

              ],
              "events": [

              ],
              "renderAttributes": {
                "class": "likert"
              },
              "dataType": "string",
              "renderType": "radio",
              "choicesResourceName": null,
              "choicesRunIf": null,
              "choices": [
                {
                  "label": "Strongly Agree",
                  "value": "Strongly Agree"
                },
                {
                  "label": "Agree",
                  "value": "Agree"
                },
                {
                  "label": "Neutral",
                  "value": "Neutral"
                },
                {
                  "label": "Disagree",
                  "value": "Disagree"
                },
                {
                  "label": "Strongly Disagree",
                  "value": "Strongly Disagree"
                }
              ]
            },
            {
              "type": "field",
              "name": "Example Question 2",
              "label": "Example Question 2",
              "key": "f918",
              "defaultValue": "",
              "defaultResourceName": null,
              "visible": true,
              "enabled": true,
              "required": false,
              "requiredMessage": null,
              "omitWhenHidden": null,
              "pattern": null,
              "constraints": [

              ],
              "events": [

              ],
              "renderAttributes": {
                "class": "likert"
              },
              "dataType": "string",
              "renderType": "radio",
              "choicesResourceName": null,
              "choicesRunIf": null,
              "choices": [
                {
                  "label": "Strongly Agree",
                  "value": "Strongly Agree"
                },
                {
                  "label": "Agree",
                  "value": "Agree"
                },
                {
                  "label": "Neutral",
                  "value": "Neutral"
                },
                {
                  "label": "Disagree",
                  "value": "Disagree"
                },
                {
                  "label": "Strongly Disagree",
                  "value": "Strongly Disagree"
                }
              ]
            }
          ]
        },
        {
          "type": "section",
          "renderType": null,
          "name": "Survey Comments",
          "title": null,
          "visible": true,
          "omitWhenHidden": null,
          "renderAttributes": {
          },
          "elements": [
            {
              "type": "field",
              "name": "Additional Comments",
              "label": "Additional Comments",
              "key": "f915",
              "defaultValue": null,
              "defaultResourceName": null,
              "visible": true,
              "enabled": true,
              "required": false,
              "requiredMessage": null,
              "omitWhenHidden": null,
              "pattern": null,
              "constraints": [

              ],
              "events": [

              ],
              "renderAttributes": {
              },
              "dataType": "string",
              "renderType": "text",
              "rows": 2
            }
          ]
        },
        {
          "type": "section",
          "renderType": null,
          "name": "Footer",
          "title": null,
          "visible": true,
          "omitWhenHidden": null,
          "renderAttributes": {
            "class": "text-right"
          },
          "elements": [
            {
              "type": "button",
              "label": "Submit",
              "name": "Submit",
              "visible": true,
              "enabled": true,
              "renderType": "submit-page",
              "renderAttributes": {
              }
            }
          ]
        },
        {
          "type": "section",
          "renderType": null,
          "name": "Hidden System Questions Do Not Delete",
          "title": "Hidden System Questions Do Not Delete",
          "visible": false,
          "omitWhenHidden": false,
          "renderAttributes": {
          },
          "elements": [
            {
              "type": "field",
              "name": "Discussion Id",
              "label": "Discussion Id",
              "key": "f902",
              "defaultValue": null,
              "defaultResourceName": null,
              "visible": true,
              "enabled": true,
              "required": false,
              "requiredMessage": null,
              "omitWhenHidden": null,
              "pattern": null,
              "constraints": [

              ],
              "events": [

              ],
              "renderAttributes": {
              },
              "dataType": "string",
              "renderType": "text",
              "rows": 1
            },
            {
              "type": "field",
              "name": "Observing Individuals",
              "label": "Observing Individuals",
              "key": "f905",
              "defaultValue": null,
              "defaultResourceName": null,
              "visible": true,
              "enabled": true,
              "required": false,
              "requiredMessage": null,
              "omitWhenHidden": null,
              "pattern": null,
              "constraints": [

              ],
              "events": [

              ],
              "renderAttributes": {
              },
              "dataType": "json",
              "renderType": "checkbox",
              "choicesResourceName": null,
              "choicesRunIf": null,
              "choices": [

              ]
            },
            {
              "type": "field",
              "name": "Observing Teams",
              "label": "Observing Teams",
              "key": "f904",
              "defaultValue": null,
              "defaultResourceName": null,
              "visible": true,
              "enabled": true,
              "required": false,
              "requiredMessage": null,
              "omitWhenHidden": null,
              "pattern": null,
              "constraints": [

              ],
              "events": [

              ],
              "renderAttributes": {
              },
              "dataType": "json",
              "renderType": "checkbox",
              "choicesResourceName": null,
              "choicesRunIf": null,
              "choices": [

              ]
            },
            {
              "type": "field",
              "name": "recipientEmail",
              "label": "recipientEmail",
              "key": "f908",
              "defaultValue": "",
              "defaultResourceName": null,
              "visible": true,
              "enabled": true,
              "required": false,
              "requiredMessage": null,
              "omitWhenHidden": null,
              "pattern": null,
              "constraints": [

              ],
              "events": [

              ],
              "renderAttributes": {
              },
              "dataType": "string",
              "renderType": "text",
              "rows": 1
            },
            {
              "type": "field",
              "name": "Reference Id",
              "label": "Reference Id",
              "key": "f916",
              "defaultValue": null,
              "defaultResourceName": null,
              "visible": true,
              "enabled": true,
              "required": false,
              "requiredMessage": null,
              "omitWhenHidden": null,
              "pattern": null,
              "constraints": [

              ],
              "events": [

              ],
              "renderAttributes": {
              },
              "dataType": "string",
              "renderType": "text",
              "rows": 1
            },
            {
              "type": "field",
              "name": "Status",
              "label": "Status",
              "key": "f901",
              "defaultValue": "Draft",
              "defaultResourceName": null,
              "visible": true,
              "enabled": true,
              "required": false,
              "requiredMessage": null,
              "omitWhenHidden": null,
              "pattern": null,
              "constraints": [

              ],
              "events": [

              ],
              "renderAttributes": {
              },
              "dataType": "string",
              "renderType": "text",
              "rows": 1
            },
            {
              "type": "field",
              "name": "Assigned Individual",
              "label": "Assigned Individual",
              "key": "f919",
              "defaultValue": null,
              "defaultResourceName": null,
              "visible": true,
              "enabled": true,
              "required": false,
              "requiredMessage": null,
              "omitWhenHidden": null,
              "pattern": null,
              "constraints": [

              ],
              "events": [

              ],
              "renderAttributes": {
              },
              "dataType": "string",
              "renderType": "text",
              "rows": 1
            }
          ]
        },
        {
          "type": "section",
          "renderType": null,
          "name": "Questions from Source",
          "title": null,
          "visible": false,
          "omitWhenHidden": false,
          "renderAttributes": {
          },
          "elements": [
            {
              "type": "field",
              "name": "d-Example Source Data",
              "label": "Example Source Data",
              "key": "f917",
              "defaultValue": null,
              "defaultResourceName": null,
              "visible": true,
              "enabled": true,
              "required": false,
              "requiredMessage": null,
              "omitWhenHidden": null,
              "pattern": null,
              "constraints": [

              ],
              "events": [

              ],
              "renderAttributes": {
              },
              "dataType": "string",
              "renderType": "text",
              "rows": 1
            }
          ]
        }
      ],
      "events": [

      ],
      "name": "Page 1",
      "renderType": "submittable",
      "type": "page"
    }
  ],
  "securityPolicies": [

  ],
  "slug": "survey-template-scale",
  "status": "Inactive",
  "submissionLabelExpression": "${form('name')} for ${values('recipientEmail')}",
  "type": "Template"
}